[
  { "code": "01", "nom": "Ain", "actif": true },
  { "code": "02", "nom": "Aisne", "actif": true },
  { "code": "02A", "nom": "Corse-du-Sud", "actif": true },
  { "code": "02B", "nom": "Haute-Corse", "actif": true },
  { "code": "03", "nom": "Allier", "actif": true },
  { "code": "04", "nom": "Alpes-de-Haute-Provence", "actif": true },
  { "code": "05", "nom": "Hautes-Alpes", "actif": true },
  { "code": "06", "nom": "Alpes-Maritimes", "actif": true },
  { "code": "07", "nom": "Ardèche", "actif": true },
  { "code": "08", "nom": "Ardennes", "actif": true },
  { "code": "09", "nom": "Ariège", "actif": true },
  { "code": "10", "nom": "Aube", "actif": true },
  { "code": "11", "nom": "Aude", "actif": true },
  { "code": "12", "nom": "Aveyron", "actif": true },
  { "code": "13", "nom": "Bouches-du-Rhône", "actif": true },
  { "code": "14", "nom": "Calvados", "actif": true },
  { "code": "15", "nom": "Cantal", "actif": true },
  { "code": "16", "nom": "Charente", "actif": true },
  { "code": "17", "nom": "Charente-Maritime", "actif": true },
  { "code": "18", "nom": "Cher", "actif": true },
  { "code": "19", "nom": "Corrèze", "actif": true },
  { "code": "21", "nom": "Côte-d'Or", "actif": true },
  { "code": "22", "nom": "Côtes-d'Armor", "actif": true },
  { "code": "23", "nom": "Creuse", "actif": true },
  { "code": "24", "nom": "Dordogne", "actif": true },
  { "code": "25", "nom": "Doubs", "actif": true },
  { "code": "26", "nom": "Drôme", "actif": true },
  { "code": "27", "nom": "Eure", "actif": true },
  { "code": "28", "nom": "Eure-et-Loir", "actif": true },
  { "code": "29", "nom": "Finistère", "actif": true },
  { "code": "30", "nom": "Gard", "actif": true },
  { "code": "31", "nom": "Haute-Garonne", "actif": true },
  { "code": "32", "nom": "Gers", "actif": true },
  { "code": "33", "nom": "Gironde", "actif": true },
  { "code": "34", "nom": "Hérault", "actif": true },
  { "code": "35", "nom": "Ille-et-Vilaine", "actif": true },
  { "code": "36", "nom": "Indre", "actif": true },
  { "code": "37", "nom": "Indre-et-Loire", "actif": true },
  { "code": "38", "nom": "Isère", "actif": true },
  { "code": "39", "nom": "Jura", "actif": true },
  { "code": "40", "nom": "Landes", "actif": true },
  { "code": "41", "nom": "Loir-et-Cher", "actif": true },
  { "code": "42", "nom": "Loire", "actif": true },
  { "code": "43", "nom": "Haute-Loire", "actif": true },
  { "code": "44", "nom": "Loire-Atlantique", "actif": true },
  { "code": "45", "nom": "Loiret", "actif": true },
  { "code": "46", "nom": "Lot", "actif": true },
  { "code": "47", "nom": "Lot-et-Garonne", "actif": true },
  { "code": "48", "nom": "Lozère", "actif": true },
  { "code": "49", "nom": "Maine-et-Loire", "actif": true },
  { "code": "50", "nom": "Manche", "actif": true },
  { "code": "51", "nom": "Marne", "actif": true },
  { "code": "52", "nom": "Haute-Marne", "actif": true },
  { "code": "53", "nom": "Mayenne", "actif": true },
  { "code": "54", "nom": "Meurthe-et-Moselle", "actif": true },
  { "code": "55", "nom": "Meuse", "actif": true },
  { "code": "56", "nom": "Morbihan", "actif": true },
  { "code": "57", "nom": "Moselle", "actif": true },
  { "code": "58", "nom": "Nièvre", "actif": true },
  { "code": "59", "nom": "Nord", "actif": true},
  { "code": "60", "nom": "Oise", "actif": true },
  { "code": "61", "nom": "Orne", "actif": true },
  { "code": "62", "nom": "Pas-de-Calais", "actif": true },
  { "code": "63", "nom": "Puy-de-Dôme", "actif": true },
  { "code": "64", "nom": "Pyrénées-Atlantiques", "actif": true },
  { "code": "65", "nom": "Hautes-Pyrénées", "actif": true },
  { "code": "66", "nom": "Pyrénées-Orientales", "actif": true },
  { "code": "67", "nom": "Bas-Rhin", "actif": true },
  { "code": "68", "nom": "Haut-Rhin", "actif": true },
  { "code": "69", "nom": "Rhône", "actif": true },
  { "code": "70", "nom": "Haute-Saône", "actif": true },
  { "code": "71", "nom": "Saône-et-Loire", "actif": true },
  { "code": "72", "nom": "Sarthe", "actif": true },
  { "code": "73", "nom": "Savoie", "actif": true },
  { "code": "74", "nom": "Haute-Savoie", "actif": true },
  { "code": "75", "nom": "Paris", "actif": true },
  { "code": "76", "nom": "Seine-Maritime", "actif": true },
  { "code": "77", "nom": "Seine-et-Marne", "actif": true },
  { "code": "78", "nom": "Yvelines", "actif": true },
  { "code": "79", "nom": "Deux-Sèvres", "actif": true },
  { "code": "80", "nom": "Somme", "actif": true },
  { "code": "81", "nom": "Tarn", "actif": true },
  { "code": "82", "nom": "Tarn-et-Garonne", "actif": true },
  { "code": "83", "nom": "Var", "actif": true },
  { "code": "84", "nom": "Vaucluse", "actif": true },
  { "code": "85", "nom": "Vendée", "actif": true },
  { "code": "86", "nom": "Vienne", "actif": true },
  { "code": "87", "nom": "Haute-Vienne", "actif": true },
  { "code": "88", "nom": "Vosges", "actif": true },
  { "code": "89", "nom": "Yonne", "actif": true },
  { "code": "90", "nom": "Territoire de Belfort", "actif": true },
  { "code": "91", "nom": "Essonne", "actif": true },
  { "code": "92", "nom": "Hauts-de-Seine", "actif": true },
  { "code": "93", "nom": "Seine-Saint-Denis", "actif": true },
  { "code": "94", "nom": "Val-de-Marne", "actif": true },
  { "code": "95", "nom": "Val-d'Oise", "actif": true },
  { "code": "971", "nom": "Guadeloupe", "actif": true },
  { "code": "972", "nom": "Martinique", "actif": true },
  { "code": "973", "nom": "Guyane", "actif": true },
  { "code": "974", "nom": "La Réunion", "actif": true },
  { "code": "975", "nom": "Saint-Pierre-et-Miquelon", "actif": true },
  { "code": "976", "nom": "Mayotte", "actif": true },
  { "code": "977", "nom": "Saint-Barthélémy", "actif": true },
  { "code": "978", "nom": "Saint-Martin", "actif": true },
  { "code": "986", "nom": "Wallis et Futuna", "actif": true },
  { "code": "987", "nom": "Polynésie française", "actif": true },
  { "code": "988", "nom": "Nouvelle-Calédonie", "actif": true }   
]
